[
  {
    "id": 1,
    "linkSrc": "#oProgramie",
    "linkName": "o programie",
    "side": "L"
  },
  {
    "id": 2,
    "linkSrc": "#punktyPomocy",
    "linkName": "punkty pomocy",
    "side": "L"
  },
  {
    "id": 3,
    "linkSrc": "#oNas",
    "linkName": "Kim jesteśmy?",
    "side": "L"
  },
  {
    "id": 4,
    "linkSrc": "ogloszenia",
    "linkName": "Ogłoszenia",
    "side": "R"
  },
  {
    "id": 5,
    "linkSrc": "harmonogramy",
    "linkName": "Harmonogramy",
    "side": "R"
  },
  {
    "id": 6,
    "linkSrc": "dopobrania",
    "linkName": "Do pobrania",
    "side": "R"
  },
  {
    "id": 7,
    "linkSrc": "#kontakt",
    "linkName": "kontakt",
    "side": "R"
  }
]
